setup.py
Products/__init__.py
Products.PageTemplateFilledSlots.egg-info/PKG-INFO
Products.PageTemplateFilledSlots.egg-info/SOURCES.txt
Products.PageTemplateFilledSlots.egg-info/dependency_links.txt
Products.PageTemplateFilledSlots.egg-info/entry_points.txt
Products.PageTemplateFilledSlots.egg-info/namespace_packages.txt
Products.PageTemplateFilledSlots.egg-info/not-zip-safe
Products.PageTemplateFilledSlots.egg-info/requires.txt
Products.PageTemplateFilledSlots.egg-info/top_level.txt
Products/PageTemplateFilledSlots/__init__.py
Products/PageTemplateFilledSlots/changes.txt
Products/PageTemplateFilledSlots/configure.zcml
Products/PageTemplateFilledSlots/readme.txt
Products/PageTemplateFilledSlots/tests.py
Products/PageTemplateFilledSlots/zope2.py