Metadata-Version: 1.0
Name: Products.PageTemplateFilledSlots
Version: 1.0.1
Summary: Gives the template variable in page templates a method pt_filled_slots to see which slots are being filled
Home-page: http://www.nidelven-it.no/d
Author: Morten W. Petersen
Author-email: info@nidelven-it.no
License: GPL
Keywords: python zope pagetemplates tal tales
Platform: UNKNOWN
Classifier: Programming Language :: Python
Classifier: Framework :: Zope2
